Metadata-Version: 2.4
Name: archr
Version: 9.2.165
Summary: Target-centric program analysis.
Home-page: https://github.com/angr/archr
License: BSD-2-Clause
Classifier: Operating System :: POSIX :: Linux
Classifier: Programming Language :: Python :: 3
Classifier: Programming Language :: Python :: 3 :: Only
Requires-Python: >=3.9
License-File: LICENSE
Requires-Dist: cle==9.2.165
Requires-Dist: docker
Requires-Dist: nclib>=1.0.0rc3
Requires-Dist: patchelf-wrapper
Requires-Dist: ply
Requires-Dist: pygdbmi
Requires-Dist: shellphish-qemu>=0.12.2
Provides-Extra: angr
Requires-Dist: angr==9.2.165; extra == "angr"
Provides-Extra: bintrace
Requires-Dist: bintrace; extra == "bintrace"
Provides-Extra: qtrace
Requires-Dist: qtrace; extra == "qtrace"
Dynamic: license-file
